ngl_tools/__init__.py
ngl_tools/smt.py
ngl_tools-1.0.6.dist-info/LICENSE
ngl_tools-1.0.6.dist-info/METADATA
ngl_tools-1.0.6.dist-info/WHEEL
ngl_tools-1.0.6.dist-info/RECORD
