Metadata-Version: 2.3
Name: ngl_tools
Version: 1.0.6
Summary: A collection of software tools developed by the Next Generation Liquefaction modeling teams
License: LICENSE.txt
Author: Scott J. Brandenberg
Requires-Python: >=3.8
Classifier: License :: Other/Proprietary License
Classifier: Programming Language :: Python :: 3
Classifier: Programming Language :: Python :: 3.8
Classifier: Programming Language :: Python :: 3.9
Classifier: Programming Language :: Python :: 3.10
Classifier: Programming Language :: Python :: 3.11
Classifier: Programming Language :: Python :: 3.12
Classifier: Programming Language :: Python :: 3.13
Requires-Dist: numpy (>=1.22)
